hknlp/__init__.py
hknlp/collator.py
hknlp/data.py
hknlp/prompt.json
hknlp/prompt.py
hknlp/spelling.py
hknlp/synonym.py
hknlp/translation.py
hknlp/utils.py
hknlp/data/prompt.json
hknlp/data/synonyms.json
hk_nlp-1.0.2.5.dist-info/METADATA
hk_nlp-1.0.2.5.dist-info/WHEEL
hk_nlp-1.0.2.5.dist-info/top_level.txt
hk_nlp-1.0.2.5.dist-info/RECORD
