Metadata-Version: 2.1
Name: hk-nlp
Version: 1.0.2.5
Summary: personal package
Home-page: UNKNOWN
Author: psyche
Author-email: hkjeon13@gmail.com
License: MIT
Platform: UNKNOWN
Requires-Python: >=3
Requires-Dist: transformers
Requires-Dist: datasets
Requires-Dist: requests
